frozendict/cool.py
frozendict/version.py
frozendict/__init__.pyi
frozendict/__init__.py
frozendict/core.py
frozendict/py.typed
frozendict/_frozendict_py.py
frozendict/monkeypatch.py
frozendict/_frozendict.cpython-39-darwin.so
frozendict-2.4.7.dist-info/RECORD
frozendict-2.4.7.dist-info/WHEEL
frozendict-2.4.7.dist-info/top_level.txt
frozendict-2.4.7.dist-info/METADATA
frozendict-2.4.7.dist-info/licenses/LICENSE.txt
