Metadata-Version: 2.1
Name: frozendict
Version: 2.4.7
Summary: A simple immutable dictionary
Home-page: https://github.com/Marco-Sulla/python-frozendict
Author: Marco Sulla
Author-email: marcosullaroma@gmail.com
License: LGPL v3
Project-URL: Bug Reports, https://github.com/Marco-Sulla/python-frozendict/issues
Project-URL: Source, https://github.com/Marco-Sulla/python-frozendict
Keywords: immutable hashable picklable frozendict dict dictionary map Mapping MappingProxyType developers stable utility
Classifier: Development Status :: 5 - Production/Stable
Classifier: Intended Audience :: Developers
Classifier: License :: OSI Approved :: GNU Lesser General Public License v3 (LGPLv3)
Classifier: Programming Language :: Python :: 3 :: Only
Classifier: Programming Language :: Python :: 3.6
Classifier: Natural Language :: English
Classifier: Operating System :: OS Independent
Classifier: Topic :: Software Development :: Libraries
Classifier: Topic :: Software Development :: Libraries :: Python Modules
Classifier: Topic :: Utilities
Requires-Python: >=3.6
License-File: LICENSE.txt
